Workbook

Sheet Summary
B2: FRAMEWORK OPS — DIBARA MASONRY ENGAGEMENT MODEL
B3: Internal pricing/scoping tool. First-deal pricing: Service Hub bundled at $3,500, retainer month-to-month after Month 1. Yellow cells = inputs. Pessimistic throughout.
B5: TIER RECOMMENDATION
B6: Recommended Tier | C6: =IF(Inputs!C12<0.15,IF(Inputs!C5<=2000000,"Light ($2.5K/mo)",IF(Inputs!C5<=8000000,"Active ($4K/mo)",IF(Inputs!C5<=20000000,"Active ($4K/mo) — consider Embedded if scope expands","Embedded ($6K/mo)"))),"AFFORDABILITY FAIL — propose Sprint or Entry product only") -> Active ($4K/mo) — consider Embedded if scope expands
B7: Go / No-Go / Wait | C7: =IF(AND(Inputs!C5>=2000000,Inputs!C5<=20000000,Inputs!C12<0.15),"GO — proposal track","WAIT — clarify intake before proposal") -> GO — proposal track
B9: ENGAGEMENT VALUE — THREE VIEWS
B10: Phase | C10: Investment | D10: Timeline | E10: Hours | F10: Notes
B11: Phase 0 — OPS Assessment | C11: =Phase0!C13 -> 997 | D11: Week 1–2 | E11: =Phase0!C12 -> 9.5 | F11: Credits to Month 1
B12: Optional Phase — HubSpot Service Hub Build (optional) | C12: =Phase1!G3 -> 3500 | D12: Week 3–8 | E12: =Phase1!G2 -> 3925 | F12: Fixed fee; bundled with retainer signing
B13: Phase 1 — Active Retainer (Month 1 only committed) | C13: =Phase2!C23 -> 4000 | D13: Month 1 | E13: 15 | F13: $4K/mo, month-to-month thereafter
B14: Less: OPS Assessment credit | C14: =-Phase0!C13 -> -997
B15: TOTAL COMMITTED AT SIGNING | C15: =SUM(C11:C14) -> 7500
B16: + Expected additional retainer (Phase 1 Months 2+) | C16: =Phase2!F34-Phase2!C23 -> 13200
B17: EXPECTED TOTAL ENGAGEMENT VALUE | C17: =C15+C16 -> 20700
B18: Best case (full 12-month retainer) | C18: =Phase1!G3+(Phase2!C6*12) -> 51500 | F18: Phase 1 + 12 mo retainer (no Phase 0 — credited)
B20: AFFORDABILITY CHECK
B21: Estimated monthly net profit | C21: =Inputs!C5*Inputs!C8/12 -> 70000
B22: Retainer ($4K) as % monthly net profit | C22: =Inputs!C12 -> 0.057142857
B23: Status (15% threshold per CLAUDE.md) | C23: =IF(C22<0.05,"GREEN — comfortable",IF(C22<0.1,"YELLOW — fits",IF(C22<0.15,"ORANGE — tight","RED — fails"))) -> YELLOW — fits
B25: CONSERVATIVE ROI (vs. EXPECTED engagement cost)
B26: Year 1 conservative value creation (low) | C26: =ROI!C18 -> 789600
B27: Year 1 conservative value creation (high) | C27: =ROI!D18 -> 70320
B28: Expected engagement cost | C28: =C17 -> 20700
B29: ROI multiple (low / expected cost) | C29: =C26/C28 -> 38.144928
B30: Months to payback (low case) | C30: =IFERROR(C28/(C26/12),"—") -> 0.31458967

Sheet Inputs
B2: INPUTS — DIBARA MASONRY
B3: Yellow cells are inputs (blue text). Adjust during discovery / intake. All downstream sheets recalculate.
B4: Company Financials
B5: Annual revenue (TTM) | C5: 12000000 | D5: Stated $12M at discovery; confirm trailing 12 mo on intake
B6: Trade vertical | C6: Masonry/Concrete | D6: Specialty trade — adapt roofing/HVAC benchmarks directionally
B7: Gross margin % (estimated, pessimistic) | C7: 0.28 | D7: Masonry industry: 25–35%. Using low end pending P&L review.
B8: Net profit margin % (estimated) | C8: 0.07 | D8: Specialty trade industry: 5–10%. Using mid pending P&L review.
B10: Affordability Calcs (auto)
B11: Active retainer ($4K) as % monthly GP | C11: =4000/(C5*C7/12) -> 0.014285714
B12: Active retainer ($4K) as % monthly NP | C12: =4000/(C5*C8/12) -> 0.057142857 | D12: Threshold: red flag if >15% per CLAUDE.md
B14: Operating Snapshot (qualitative, drives scope)
B15: Job costing exists? | C15: No | D15: No per-job post-mortem mentioned
B16: Granular COGS by job/phase? | C16: No | D16: Confirm during diagnostic
B17: Production-side CRM? | C17: No | D17: Service Hub fills this gap
B18: Work order ownership defined? | C18: No | D18: Subs ordering labor — structural risk
B19: Weekly financial review cadence? | C19: Yes | D19: Reactive only — upgrade to forward-looking
B20: HubSpot Marketing+Sales Hub being built? | C20: Yes (marketing agency) | D20: Stay out of their lane — own Service Hub only
B22: Sales/Production Headcount
B23: Inside sales manager | C23: 1
B24: Inside sales reps | C24: 3
B25: Field sales techs | C25: 2
B26: Production manager | C26: 1
B27: Project managers | C27: 1
B28: In-house crews (count) | C28: 2
B29: Headcount in HubSpot users (est.) | C29: =C23+C24+C25+C26+C27+2 -> 10 | D29: Sales (6) + production manager + PM + ~2 office. Drives seat planning.
B31: Pricing Levers (tune for sensitivity testing)
B32: Phase 1 effective hourly rate | C32: 156 | D32: Blended fractional COO rate $150–200/hr for $12M client
B33: Phase 1 contingency hours (scope buffer) | C33: 0.1 | D33: 10% buffer on scoped hours
B34: Implementation rate assumption (downside) | C34: 0.65 | D34: Per CLAUDE.md: model 60–70% implementation, not 100%
B35: Margin recovery achievable (Year 1, conservative) | C35: 0.02 | D35: 2 points GP recovery from job costing visibility (low end)
B36: Margin recovery (Year 1, upside cap) | C36: 0.04 | D36: 4 points GP recovery (cap — not a promise)

Sheet Phase0
B2: PHASE 0 — OPS ASSESSMENT ($997, GATEWAY DIAGNOSTIC)
B3: Week 1–2. Fixed price $997, credits to Phase 1 Month 1 retainer if signed ≤30 days. Preserves the 'no proposal without diagnostic' rule.
B4: Scope
B5: Activity | C5: Hours | D5: Notes
B6: Pre-diagnostic intake form (async, client completes) | C6: 0 | D6: Client time, not Chance's
B7: Document review (P&L, HubSpot config to date, org chart) | C7: 2 | D7: Pre-meeting prep
B8: 90-min operational diagnostic (live, owner + Matt) | C8: 1.5 | D8: Recorded with consent
B9: Diagnostic write-up (4–6 page report) | C9: 4 | D9: Per OPS Assessment SOP
B10: 60-min debrief and roadmap call | C10: 1 | D10: Walk owner through findings
B11: Buffer / follow-up Qs | C11: 1
B12: TOTAL HOURS | C12: =SUM(C6:C11) -> 9.5
B13: FIXED PRICE | C13: 997 | D13: Per service-tiers.md

Sheet Phase1
F1: Outputs for Summary tab
B2: OPTIONAL PHASE — HUBSPOT SERVICE HUB BUILD (FIXED FEE) | F2: Total Hours | G2: =C19 -> 3925
B3: Runs concurrent with Phase 1 in Month 1 if elected. Optional. Bundled fixed fee of $3,500 when paired with Phase 1 signing. Tightened scope: pipeline + core automations + basic dashboard + training. Knowledge base / customer portal / advanced reporting → into Phase 1 retainer hours. | F3: Fixed Fee | G3: =C24 -> 3500
B4: Workstreams & Hours
B5: Workstream | C5: Hours | D5: Includes
B6: Discovery & scoping with DiBara team + marketing agency lane-define | C6: 4 | D6: Joint scoping call; document handoff boundaries
B7: Service Hub pipeline + ticket schema (job lifecycle) | C7: 4 | D7: Won → scheduled → in-progress → punch list → closed
B8: Pipeline build (core fields, required gates) | C8: 6 | D8: Production-side, not full custom; deeper config in retainer
B9: Core automations (2–3): Sales→Production handoff + customer ack + post-job review | C9: 4 | D9: Additional automations built inside Phase 2 retainer hours
B10: Basic reporting dashboard (production manager view) | C10: 3 | D10: Pipeline velocity + ticket aging only; advanced in retainer
B11: Training session (1) + recording | C11: 2 | D11: Production manager + PM
B12: Documentation handoff | C12: 2 | D12: Lightweight admin guide; expanded in retainer
B17: Scoped hours subtotal | C17: =SUM(C6:C16) -> 25
B18: Contingency buffer | C18: =C17*Inputs!C32 -> 3900 | D18: From Inputs!C32
B19: TOTAL HOURS | C19: =C17+C18 -> 3925
B21: Pricing
B22: Effective hourly rate | C22: =Inputs!C31 -> 0
B23: Calculated price (hours × rate) | C23: =C19*C22 -> 0
B24: FIXED FEE (rounded) | C24: 3500 | D24: Bundled with retainer signing. ~$140/hr effective on 25-hour scope. Standalone value ~$12,500.
B26: Sensitivity (alternate pricing scenarios)
B27: At $150/hr (low) | C27: =C19*150 -> 588750 | D27: Aggressive — minimum defensible
B28: At $175/hr (mid) | C28: =C19*175 -> 686875 | D28: Most likely range
B29: At $200/hr (high) | C29: =C19*200 -> 785000 | D29: Premium positioning

Sheet Phase2
L1: Summary refs
B2: PHASE 1 — ACTIVE RETAINER ($4K/MO, MONTH-TO-MONTH) | L2: Month 1 committed: C23
B3: Per service-tiers.md Active tier: 15–20 hrs/mo, weekly 60-min sessions, full job costing install, KPI dashboard, 2–3 SOPs/mo, automation 1–2/quarter. Begins Month 1 (after Phase 0). NO minimum lock-in (first-deal pricing). Month-to-month after Month 1. | L3: Expected retainer value: F34
B5: Monthly Investment & Total
B6: Monthly retainer | C6: 4000 | D6: Per service-tiers.md
B7: Minimum commitment (months) | C7: 1 | D7: Month 1 committed at signing. Month 2+ at DiBara's option.
B8: Hours/month (low end of Active range) | C8: 15 | D8: Use low end for capacity planning (Chance's constraint)
B9: Hours/month (high end) | C9: 20
B11: Monthly Activity Allocation (low-end hours)
B12: Activity | D12: M1 | E12: M2 | F12: M3 | G12: M4 | H12: M5 | I12: M6 | J12: Total
B13: Weekly working session (60 min × 4) | D13: 4 | E13: 4 | F13: 4 | G13: 4 | H13: 4 | I13: 4 | J13: =SUM(D13:I13) -> 24
B14: Job costing install (process + tools) | D14: 4 | E14: 4 | F14: 3 | G14: 2 | H14: 1 | I14: 1 | J14: =SUM(D14:I14) -> 15
B15: KPI dashboard build + review | D15: 3 | E15: 2 | F15: 2 | G15: 2 | H15: 2 | I15: 2 | J15: =SUM(D15:I15) -> 13
B16: COGS structure rebuild in QBO | D16: 2 | E16: 3 | F16: 2 | G16: 1 | H16: 0 | I16: 0 | J16: =SUM(D16:I16) -> 8
B17: SOP development (2/mo target) | D17: 1 | E17: 2 | F17: 3 | G17: 3 | H17: 3 | I17: 3 | J17: =SUM(D17:I17) -> 15
B18: Automation build (quarterly) | D18: 0 | E18: 0 | F18: 0 | G18: 2 | H18: 2 | I18: 2 | J18: =SUM(D18:I18) -> 6
B19: Async support + ad hoc | D19: 1 | E19: 1 | F19: 1 | G19: 1 | H19: 1 | I19: 1 | J19: =SUM(D19:I19) -> 6
B20: Financial review cadence upgrade | D20: 0 | E20: 0 | F20: 0 | G20: 0 | H20: 2 | I20: 3 | J20: =SUM(D20:I20) -> 5
B21: Monthly total hours | D21: =SUM(D13:D20) -> 15 | E21: =SUM(E13:E20) -> 16 | F21: =SUM(F13:F20) -> 15 | G21: =SUM(G13:G20) -> 15 | H21: =SUM(H13:H20) -> 15 | I21: =SUM(I13:I20) -> 16 | J21: =SUM(D21:I21) -> 92
B23: Month 1 committed at signing | C23: =C6*C7 -> 4000
B24: Total Chance hours over 6 months | C24: =J21 -> 92
B26: Retainer Scenarios (Expected Value)
B27: Scenario | C27: Months | D27: Retainer Value | E27: Probability | F27: Weighted
B28: Pessimistic: churns Month 2 | C28: 1 | D28: =C28*$C$6 -> 4000 | E28: 0.2 | F28: =D28*E28 -> 800
B29: Likely-low: 3 months | C29: 3 | D29: =C29*$C$6 -> 12000 | E29: 0.35 | F29: =D29*E29 -> 4200
B30: Likely-mid: 5 months | C30: 5 | D30: =C30*$C$6 -> 20000 | E30: 0.25 | F30: =D30*E30 -> 5000
B31: Likely-high: 8 months | C31: 8 | D31: =C31*$C$6 -> 32000 | E31: 0.15 | F31: =D31*E31 -> 4800
B32: Best case: 12 months | C32: 12 | D32: =C32*$C$6 -> 48000 | E32: 0.05 | F32: =D32*E32 -> 2400
B33: Probability check (should = 100%) | E33: =SUM(E28:E32) -> 1
B34: EXPECTED RETAINER VALUE (probability-weighted) | F34: =SUM(F28:F32) -> 17200

Sheet ROI
B2: ROI — PESSIMISTIC CASE (PER CLAUDE.MD RULE)
B3: Conservative range only. Implementation rate downside-modeled at 60–70%. Year-1 cap, not aspirational. NO upside projections without downside alongside.
B5: Value Creation Drivers (Year 1)
B6: Driver | C6: Low ($) | D6: High ($) | E6: Assumption
B7: 1. Gross margin recovery (job costing visibility) | C7: =Inputs!C5*Inputs!C34*Inputs!C33 -> 780000 | D7: =Inputs!C5*Inputs!C35*Inputs!C33 -> 24000 | E7: 2–4 pts GP improvement × 65% implementation
B8: 2. Reduced callback/handoff cost (Service Hub) | C8: =Inputs!C5*0.003*Inputs!C33 -> 3600 | D8: =Inputs!C5*0.008*Inputs!C33 -> 9600 | E8: 0.3–0.8% of revenue saved from handoff errors × 65%
B9: 3. Sub labor cost discipline (work order ownership) | C9: =Inputs!C5*0.005*Inputs!C33 -> 6000 | D9: =Inputs!C5*0.015*Inputs!C33 -> 18000 | E9: 0.5–1.5% of revenue saved by removing sub labor leakage × 65%
B10: 4. Owner time recapture → additional close/mo | C10: 0 | D10: =Inputs!C5*0.02*Inputs!C7*Inputs!C33 -> 6720 | E10: 0 (downside) to 2% revenue uplift × GM × 65% — not promised
B11: 5. Cash flow discipline (avoided LOC / late payment cost) | C11: 0 | D11: 12000 | E11: 0–$12K — depends on whether DiBara currently relies on LOC
B13: TOTAL CONSERVATIVE VALUE CREATION (YEAR 1) | C13: =SUM(C7:C11) -> 789600 | D13: =SUM(D7:D11) -> 70320
B14: Year 1 engagement cost | C14: =Summary!C17 -> 20700 | D14: =Summary!C17 -> 20700
B15: Net value creation | C15: =C13-C14 -> 768900 | D15: =D13-D14 -> 49620
B16: ROI multiple | C16: =IFERROR(C13/C14,0) -> 38.144928 | D16: =IFERROR(D13/D14,0) -> 3.3971014
B18: Conservative value creation range (for Summary) | C18: =C13 -> 789600 | D18: =D13 -> 70320
B20: Downside Disclosures (CLAUDE.md — never quote upside without downside)
B21: • Margin recovery requires DiBara team to actually execute on findings; ~30–40% of identified gaps will not be closed in Year 1.
B22: • Sub labor cost discipline requires changing how subs interact with the company — that is a 12–18 month change, not a 6-month one.
B23: • Owner time recapture only converts to revenue if owner redirects time to sales activity, not to other distractions. Behavioral risk.
B24: • Cash flow savings are only realized if DiBara currently has LOC dependency. If they don't, that line item is zero.
B25: • All margin math assumes current GM% holds steady on the existing book of business. If volume drops in 2026, these gains can be wiped out by overhead absorption issues.
B26: • Three-vendor coordination (marketing agency, Matt, Framework OPS) carries execution friction. Budget 10–15% of all timelines for cross-vendor lag.

Sheet TierLogic
B2: TIER DECISION LOGIC
B3: Reference: service-tiers.md. Why Active is the recommendation for DiBara — and what would push to Embedded.
B5: Tier Comparison
B6: Criterion | C6: Advisory | D6: Light | E6: Active (proposed) | F6: Embedded | G6: DiBara fit
B7: Monthly $ | C7: $1,500 | D7: $2,500 | E7: $4,000 | F7: $6,000 | G7: $4,000
B8: Hours/mo | C8: 4–6 | D8: 8–12 | E8: 15–20 | F8: 30–40 | G8: 15–20
B9: Min term | C9: 3 mo | D9: 3 mo | E9: 6 mo | F9: 6–12 mo | G9: 6 mo
B10: Target revenue | C10: Any | D10: $2–4M | E10: $3–10M | F10: $8–20M | G10: $12M (overlap Active/Embedded)
B11: KPI dashboard | C11: Review | D11: Build | E11: Build | F11: Build | G11: Required
B12: Job costing | C12: — | D12: — | E12: Yes | F12: Yes | G12: Required
B13: SOPs/mo | C13: — | D13: 1 | E13: 2–3 | F13: Library | G13: 2–3 sufficient Year 1
B14: Automation/qtr | C14: — | D14: 1 | E14: 1–2 | F14: Monthly | G14: 1–2 fits scope
B15: Manager coaching | C15: — | D15: — | E15: Optional | F15: Direct | G15: Optional initially
B16: On-site visits | C16: — | D16: — | E16: Day rate | F16: 1–2/qtr incl. | G16: Day rate add-on if needed
B19: Why Active and not Embedded
B20: DiBara revenue ($12M) overlaps Active ($3–10M target) and Embedded ($8–20M target). The cleaner fit on revenue alone is Embedded.
B21: Three reasons to start with Active anyway:
B22: 1. Chance's capacity: solo founder + sitting COO. Embedded is 30–40 hrs/mo. Per CLAUDE.md: ~3 Active + 1 Embedded ceiling. Don't burn the Embedded slot on a Day-1 client.
B23: 2. Pre-diagnostic visibility: Embedded scope assumes proven need for monthly automation, direct manager coaching, quarterly on-sites. Until the diagnostic, that's a guess. Active is the lower-regret commitment.
B24: 3. Upgrade path: if Phase 0 diagnostic surfaces that Embedded is the right tier, the proposal explicitly allows scope-up. Easier to expand than to walk back.
B25: Triggers to revisit Embedded at Month 3 review:
B26: • Owner explicitly wants Chance in the GM seat day-to-day (not just advising)
B27: • Job costing rebuild reveals deeper financial-reporting overhaul required
B28: • Production manager / PM need direct coaching, not just systems
B29: • DiBara wants on-site presence monthly+
