Workbook

Sheet README
A1: Framework OPS — Solo Capacity & Revenue Model
A3: Built: May 2026 | Purpose: Stress-test the path to $150K Framework OPS revenue by Dec 2027.
A5: How to use this model
A6: 1. Inputs sheet | B6: All blue cells are levers you can change. Yellow fills mark the highest-impact inputs. Black formulas update automatically.
A7: 2. Capacity sheet | B7: Shows how your weekly hours translate to delivery capacity, after automation and utilization adjustments. Tells you the theoretical maximum portfolio you can run solo.
A8: 3. Portfolio Cap sheet | B8: Three preset scenarios (Active-heavy / Mixed / Embedded-dominant) plus your own custom mix. Shows annual revenue at each.
A9: 4. MRR Ramp sheet | B9: Month-by-month forecast from May 2026 to Dec 2027. Enter the # of each retainer tier you expect each month. Outputs MRR, run-rate, and target gap.
A10: 5. Cash Flow sheet | B10: Personal cash burn alongside Framework revenue. Models W-2 phase-out at the month you specify. POC threshold check flags whether you can responsibly leave the W-2.
A11: 6. Dashboard sheet | B11: Top-line outputs: Dec 2027 MRR, run-rate, cumulative revenue, lowest cash balance, target hit / miss.
A13: Color conventions
A14: Blue text | B14: Hardcoded input — change this
A15: Black text | B15: Formula — do not edit directly
A16: Green text | B16: Pulled from another sheet
A17: Yellow background | B17: High-impact assumption — review carefully
A18: Green background | B18: Key output
A19: Orange background | B19: Warning / threshold not met
A21: Pessimism is the default.
A22: All defaults use the low end of benchmark ranges. Assumes 60–70% client implementation, 30% annual churn, sales cycles of 4–8 weeks. Run optimistic cases only after the pessimistic case clears.

Sheet Dashboard
A1: Dashboard — Key Outputs
A2: Top-line summary. All numbers pull from the working sheets.
A4: REVENUE
A5: Dec 2027 MRR | B5: ='MRR Ramp'!G24 -> 12500
A6: Dec 2027 Annualized Run-rate | B6: ='MRR Ramp'!K24 -> 171964
A7: Target ($150K) | B7: 150000
A8: Run-rate as % of target | B8: ='MRR Ramp'!K24/150000 -> 1.1464267
A9: Total revenue 2026 (May-Dec) | B9: =SUM('MRR Ramp'!I5:I12) -> 37982
A10: Total revenue 2027 (full year) | B10: =SUM('MRR Ramp'!I13:I24) -> 153964
A11: Cumulative revenue May 2026-Dec 2027 | B11: ='MRR Ramp'!J24 -> 191946
A13: CAPACITY
A14: Phase 2 monthly delivery capacity | B14: =Capacity!B15 -> 92.8 | C14: hrs/mo
A15: Dec 2027 hours used | B15: ='MRR Ramp'!L24 -> 47.55 | C15: hrs/mo
A16: Dec 2027 capacity utilization | B16: ='MRR Ramp'!M24 -> 0.51239224
A17: Solo cap (Scenario B annual revenue) | B17: =Capacity!B25 -> 318000
A18: Target as % of solo cap | B18: =Capacity!B26 -> 0.47169811
A20: CASH FLOW
A21: Final cash balance (Dec 2027) | B21: ='Cash Flow'!L24 -> 34345.12
A22: Lowest cash balance during period | B22: =MIN('Cash Flow'!L5:L24) -> 9040.88
A23: Month of lowest cash balance | B23: =INDEX('Cash Flow'!B5:B24,MATCH(MIN('Cash Flow'!L5:L24),'Cash Flow'!L5:L24,0)) -> Jan 2027
A24: Months with negative cash delta | B24: =COUNTIF('Cash Flow'!K5:K24,"<0") -> 8
A25: Total cash burn (months with negative delta) | B25: =SUMIF('Cash Flow'!K5:K24,"<0") -> -13884.96
A27: POC THRESHOLD AT W-2 EXIT MONTH
A28: W-2 exit month | B28: =Inputs!B24 -> 4
A29: Month label at exit | B29: =INDEX('Cash Flow'!B5:B24,Inputs!B24) -> Aug 2026
A30: MRR at exit month | B30: =INDEX('MRR Ramp'!G5:G24,Inputs!B24) -> 2500
A31: Required MRR for POC | B31: =Inputs!B40 -> 7500
A32: MRR threshold met? | B32: =IF(B30>=B31,"YES","NO") -> NO
A33: Cash at exit month | B33: =INDEX('Cash Flow'!L5:L24,Inputs!B24) -> 18091.68
A34: Required cash reserves | B34: =Inputs!B25*Inputs!B41 -> 36000
A35: Cash threshold met? | B35: =IF(B33>=B34,"YES","NO") -> NO
A36: OVERALL: Safe to leave W-2? | B36: =IF(AND(B32="YES",B35="YES"),"YES","NO") -> NO

Sheet Inputs
A1: Inputs & Assumptions
A2: Change blue cells. Yellow-highlighted inputs have the biggest impact on outputs.
A4: PRICING & DELIVERY HOURS (per retainer tier)
A5: Tier | B5: Monthly fee | C5: Nominal hrs/mo | D5: Automation savings % | E5: Effective hrs/mo
A6: Advisory | B6: 1500 | C6: 5 | D6: 0.2 | E6: =C6*(1-D6) -> 4
A7: Light | B7: 2500 | C7: 10 | D7: 0.22 | E7: =C7*(1-D7) -> 7.8
A8: Active | B8: 4000 | C8: 18 | D8: 0.25 | E8: =C8*(1-D8) -> 13.5
A9: Embedded | B9: 6000 | C9: 35 | D9: 0.25 | E9: =C9*(1-D9) -> 26.25
A12: WEEKLY CAPACITY
A13: Phase 1: hours/week on Framework OPS | B13: 25 | C13: While still on $8K/mo W-2
A14: Phase 2: hours/week on Framework OPS | B14: 50 | C14: After W-2 phase-out
A15: Sales hours/week (always-on) | B15: 11 | C15: LinkedIn, outreach, discovery calls. Cannot drop.
A16: Admin hours/week | B16: 4 | C16: QBO, Mercury, scheduling, CRM, taxes
A17: Content hours/week | B17: 4 | C17: LinkedIn posts, thought leadership, batched
A18: Business dev hours/week | B18: 2 | C18: Learning, partnerships, strategic
A19: Working weeks per year | B19: 48 | C19: Allows 4 weeks off across year
A20: Capacity utilization rate | B20: 0.8 | C20: Realistic for solo — gaps, onboarding, off weeks
A22: CASH FLOW INPUTS
A23: Current W-2 monthly gross | B23: 8000 | C23: Roofing COO remote role
A24: W-2 exit month (1-20) | B24: 4 | C24: Month 1=May 2026, Month 4=Aug 2026
A25: Personal monthly expenses | B25: 6000 | C25: All-in lifestyle cost — review carefully
A26: Healthcare cost (post W-2 only) | B26: 800 | C26: Self-paid plan, single
A27: Framework OPS monthly opex | B27: 600 | C27: Tools, software, accounting, LLC compliance
A28: Effective tax rate on net SE income | B28: 0.28 | C28: Federal + SE tax + state estimate
A29: Effective tax rate on W-2 | B29: 0.22 | C29: Federal + state + FICA (your half)
A30: Starting cash reserves (May 2026) | B30: 20000 | C30: Liquid savings at model start
A32: SPRINT & ASSESSMENT REVENUE (non-retainer)
A33: Avg paid OPS Assessments / month (steady state) | B33: 1 | C33: $997 each — gateway product
A34: OPS Assessment price | B34: 997
A35: Avg sprints / quarter (steady state) | B35: 1 | C35: SOP, Automation, or Roadmap sprints
A36: Avg sprint price | B36: 2500 | C36: Midpoint of $1.5K-$3.5K range
A37: Months until sprint/assessment revenue starts | B37: 3 | C37: Initial ramp before first non-zero
A39: POC THRESHOLD (W-2 exit decision)
A40: Minimum MRR to leave W-2 | B40: 7500 | C40: Per analysis: 2 Active or 1 Active + 1 Light
A41: Minimum months of personal expenses in cash | B41: 6 | C41: 6 months recommended
A42: Minimum retainers signed with 90+ days of payment history | B42: 1 | C42: Validates the model, not just the close

Sheet Capacity
A1: Capacity Model
A2: How weekly hours translate to delivery capacity and the theoretical solo revenue ceiling.
A4: WEEKLY HOURS BREAKDOWN
A5: Activity | B5: Phase 1 hrs/wk | C5: Phase 2 hrs/wk | D5: Notes
A6: Total available | B6: =Inputs!B13 -> 25 | C6: =Inputs!B14 -> 50 | D6: From Inputs sheet
A7: Less: Sales | B7: =Inputs!B15 -> 11 | C7: =Inputs!B15 -> 11 | D7: Always-on
A8: Less: Admin | B8: =Inputs!B16 -> 4 | C8: =Inputs!B16 -> 4
A9: Less: Content | B9: =Inputs!B17 -> 4 | C9: =Inputs!B17 -> 4
A10: Less: Business dev | B10: =Inputs!B18 -> 2 | C10: =Inputs!B18 -> 2
A11: Nominal delivery hrs/wk | B11: =B6-B7-B8-B9-B10 -> 4 | C11: =C6-C7-C8-C9-C10 -> 29 | D11: Before utilization adjustment
A12: Adjusted delivery hrs/wk | B12: =B11*Inputs!B20 -> 3.2 | C12: =C11*Inputs!B20 -> 23.2 | D12: After utilization factor
A14: MONTHLY DELIVERY CAPACITY
A15: Phase 2 monthly delivery hours (steady state) | B15: =C12*Inputs!B19/12 -> 92.8 | C15: hrs/month of billable delivery available after sales/admin/utilization
A17: MAX SOLO PORTFOLIO (theoretical)
A18: Scenario | B18: Portfolio mix | C18: Hours required | D18: Monthly MRR | E18: Annual retainer revenue | F18: Hours utilized
A19: A — Active-heavy | B19: 6 Active + 1 Light | C19: =6*Inputs!E8+1*Inputs!E7 -> 88.8 | D19: =6*Inputs!B8+1*Inputs!B7 -> 26500 | E19: =D19*12 -> 318000 | F19: =C19/$B$15 -> 0.95689655
A20: B — Mixed (recommended) | B20: 2 Embedded + 3 Active + 1 Light | C20: =2*Inputs!E9+3*Inputs!E8+1*Inputs!E7 -> 100.8 | D20: =2*Inputs!B9+3*Inputs!B8+1*Inputs!B7 -> 26500 | E20: =D20*12 -> 318000 | F20: =C20/$B$15 -> 1.0862069
A21: C — Embedded-dominant | B21: 3 Embedded + 1 Active | C21: =3*Inputs!E9+1*Inputs!E8 -> 92.25 | D21: =3*Inputs!B9+1*Inputs!B8 -> 22000 | E21: =D21*12 -> 264000 | F21: =C21/$B$15 -> 0.99407328
A22: D — Target ($150K) | B22: 1 Embedded + 1 Active + 1 Light | C22: =1*Inputs!E9+1*Inputs!E8+1*Inputs!E7 -> 47.55 | D22: =1*Inputs!B9+1*Inputs!B8+1*Inputs!B7 -> 12500 | E22: =D22*12 -> 150000 | F22: =C22/$B$15 -> 0.51239224
A24: SOLO CAP SUMMARY
A25: Sustainable solo cap (Scenario B revenue) | B25: =E20 -> 318000 | C25: Add ~$30-50K/yr in sprints & assessments at the cap
A26: $150K target as % of solo cap | B26: =150000/B25 -> 0.47169811 | C26: Lower = more slack against churn and bad months

Sheet MRR Ramp
A1: MRR Ramp — May 2026 to Dec 2027
A2: Enter # of each retainer tier active per month (blue cells). All other cells calculate automatically.
A4: # | B4: Month | C4: Advisory | D4: Light | E4: Active | F4: Embedded | G4: Retainer MRR | H4: Sprint/Assess revenue | I4: Total revenue | J4: Cumulative revenue | K4: Annualized run-rate | L4: Hours used (delivery) | M4: Capacity %
A5: 1 | B5: May 2026 | C5: 0 | D5: 0 | E5: 0 | F5: 0 | G5: =C5*Inputs!$B$6+D5*Inputs!$B$7+E5*Inputs!$B$8+F5*Inputs!$B$9 -> 0 | H5: =IF(A5>=Inputs!$B$37,Inputs!$B$33*Inputs!$B$34+Inputs!$B$35/3*Inputs!$B$36,0) -> 0 | I5: =G5+H5 -> 0 | J5: =I5 -> 0 | K5: =I5*12 -> 0 | L5: =C5*Inputs!$E$6+D5*Inputs!$E$7+E5*Inputs!$E$8+F5*Inputs!$E$9 -> 0 | M5: =L5/Capacity!$B$15 -> 0
A6: 2 | B6: Jun 2026 | C6: 0 | D6: 0 | E6: 0 | F6: 0 | G6: =C6*Inputs!$B$6+D6*Inputs!$B$7+E6*Inputs!$B$8+F6*Inputs!$B$9 -> 0 | H6: =IF(A6>=Inputs!$B$37,Inputs!$B$33*Inputs!$B$34+Inputs!$B$35/3*Inputs!$B$36,0) -> 0 | I6: =G6+H6 -> 0 | J6: =J5+I6 -> 0 | K6: =I6*12 -> 0 | L6: =C6*Inputs!$E$6+D6*Inputs!$E$7+E6*Inputs!$E$8+F6*Inputs!$E$9 -> 0 | M6: =L6/Capacity!$B$15 -> 0
A7: 3 | B7: Jul 2026 | C7: 0 | D7: 1 | E7: 0 | F7: 0 | G7: =C7*Inputs!$B$6+D7*Inputs!$B$7+E7*Inputs!$B$8+F7*Inputs!$B$9 -> 2500 | H7: =IF(A7>=Inputs!$B$37,Inputs!$B$33*Inputs!$B$34+Inputs!$B$35/3*Inputs!$B$36,0) -> 1830.3333 | I7: =G7+H7 -> 4330.3333 | J7: =J6+I7 -> 4330.3333 | K7: =I7*12 -> 51964 | L7: =C7*Inputs!$E$6+D7*Inputs!$E$7+E7*Inputs!$E$8+F7*Inputs!$E$9 -> 7.8 | M7: =L7/Capacity!$B$15 -> 0.084051724
A8: 4 | B8: Aug 2026 | C8: 0 | D8: 1 | E8: 0 | F8: 0 | G8: =C8*Inputs!$B$6+D8*Inputs!$B$7+E8*Inputs!$B$8+F8*Inputs!$B$9 -> 2500 | H8: =IF(A8>=Inputs!$B$37,Inputs!$B$33*Inputs!$B$34+Inputs!$B$35/3*Inputs!$B$36,0) -> 1830.3333 | I8: =G8+H8 -> 4330.3333 | J8: =J7+I8 -> 8660.6667 | K8: =I8*12 -> 51964 | L8: =C8*Inputs!$E$6+D8*Inputs!$E$7+E8*Inputs!$E$8+F8*Inputs!$E$9 -> 7.8 | M8: =L8/Capacity!$B$15 -> 0.084051724
A9: 5 | B9: Sep 2026 | C9: 0 | D9: 1 | E9: 0 | F9: 0 | G9: =C9*Inputs!$B$6+D9*Inputs!$B$7+E9*Inputs!$B$8+F9*Inputs!$B$9 -> 2500 | H9: =IF(A9>=Inputs!$B$37,Inputs!$B$33*Inputs!$B$34+Inputs!$B$35/3*Inputs!$B$36,0) -> 1830.3333 | I9: =G9+H9 -> 4330.3333 | J9: =J8+I9 -> 12991 | K9: =I9*12 -> 51964 | L9: =C9*Inputs!$E$6+D9*Inputs!$E$7+E9*Inputs!$E$8+F9*Inputs!$E$9 -> 7.8 | M9: =L9/Capacity!$B$15 -> 0.084051724
A10: 6 | B10: Oct 2026 | C10: 0 | D10: 1 | E10: 1 | F10: 0 | G10: =C10*Inputs!$B$6+D10*Inputs!$B$7+E10*Inputs!$B$8+F10*Inputs!$B$9 -> 6500 | H10: =IF(A10>=Inputs!$B$37,Inputs!$B$33*Inputs!$B$34+Inputs!$B$35/3*Inputs!$B$36,0) -> 1830.3333 | I10: =G10+H10 -> 8330.3333 | J10: =J9+I10 -> 21321.333 | K10: =I10*12 -> 99964 | L10: =C10*Inputs!$E$6+D10*Inputs!$E$7+E10*Inputs!$E$8+F10*Inputs!$E$9 -> 21.3 | M10: =L10/Capacity!$B$15 -> 0.22952586
A11: 7 | B11: Nov 2026 | C11: 0 | D11: 1 | E11: 1 | F11: 0 | G11: =C11*Inputs!$B$6+D11*Inputs!$B$7+E11*Inputs!$B$8+F11*Inputs!$B$9 -> 6500 | H11: =IF(A11>=Inputs!$B$37,Inputs!$B$33*Inputs!$B$34+Inputs!$B$35/3*Inputs!$B$36,0) -> 1830.3333 | I11: =G11+H11 -> 8330.3333 | J11: =J10+I11 -> 29651.667 | K11: =I11*12 -> 99964 | L11: =C11*Inputs!$E$6+D11*Inputs!$E$7+E11*Inputs!$E$8+F11*Inputs!$E$9 -> 21.3 | M11: =L11/Capacity!$B$15 -> 0.22952586
A12: 8 | B12: Dec 2026 | C12: 0 | D12: 1 | E12: 1 | F12: 0 | G12: =C12*Inputs!$B$6+D12*Inputs!$B$7+E12*Inputs!$B$8+F12*Inputs!$B$9 -> 6500 | H12: =IF(A12>=Inputs!$B$37,Inputs!$B$33*Inputs!$B$34+Inputs!$B$35/3*Inputs!$B$36,0) -> 1830.3333 | I12: =G12+H12 -> 8330.3333 | J12: =J11+I12 -> 37982 | K12: =I12*12 -> 99964 | L12: =C12*Inputs!$E$6+D12*Inputs!$E$7+E12*Inputs!$E$8+F12*Inputs!$E$9 -> 21.3 | M12: =L12/Capacity!$B$15 -> 0.22952586
A13: 9 | B13: Jan 2027 | C13: 0 | D13: 1 | E13: 1 | F13: 0 | G13: =C13*Inputs!$B$6+D13*Inputs!$B$7+E13*Inputs!$B$8+F13*Inputs!$B$9 -> 6500 | H13: =IF(A13>=Inputs!$B$37,Inputs!$B$33*Inputs!$B$34+Inputs!$B$35/3*Inputs!$B$36,0) -> 1830.3333 | I13: =G13+H13 -> 8330.3333 | J13: =J12+I13 -> 46312.333 | K13: =I13*12 -> 99964 | L13: =C13*Inputs!$E$6+D13*Inputs!$E$7+E13*Inputs!$E$8+F13*Inputs!$E$9 -> 21.3 | M13: =L13/Capacity!$B$15 -> 0.22952586
A14: 10 | B14: Feb 2027 | C14: 0 | D14: 1 | E14: 2 | F14: 0 | G14: =C14*Inputs!$B$6+D14*Inputs!$B$7+E14*Inputs!$B$8+F14*Inputs!$B$9 -> 10500 | H14: =IF(A14>=Inputs!$B$37,Inputs!$B$33*Inputs!$B$34+Inputs!$B$35/3*Inputs!$B$36,0) -> 1830.3333 | I14: =G14+H14 -> 12330.333 | J14: =J13+I14 -> 58642.667 | K14: =I14*12 -> 147964 | L14: =C14*Inputs!$E$6+D14*Inputs!$E$7+E14*Inputs!$E$8+F14*Inputs!$E$9 -> 34.8 | M14: =L14/Capacity!$B$15 -> 0.375
A15: 11 | B15: Mar 2027 | C15: 0 | D15: 1 | E15: 2 | F15: 0 | G15: =C15*Inputs!$B$6+D15*Inputs!$B$7+E15*Inputs!$B$8+F15*Inputs!$B$9 -> 10500 | H15: =IF(A15>=Inputs!$B$37,Inputs!$B$33*Inputs!$B$34+Inputs!$B$35/3*Inputs!$B$36,0) -> 1830.3333 | I15: =G15+H15 -> 12330.333 | J15: =J14+I15 -> 70973 | K15: =I15*12 -> 147964 | L15: =C15*Inputs!$E$6+D15*Inputs!$E$7+E15*Inputs!$E$8+F15*Inputs!$E$9 -> 34.8 | M15: =L15/Capacity!$B$15 -> 0.375
A16: 12 | B16: Apr 2027 | C16: 0 | D16: 1 | E16: 2 | F16: 0 | G16: =C16*Inputs!$B$6+D16*Inputs!$B$7+E16*Inputs!$B$8+F16*Inputs!$B$9 -> 10500 | H16: =IF(A16>=Inputs!$B$37,Inputs!$B$33*Inputs!$B$34+Inputs!$B$35/3*Inputs!$B$36,0) -> 1830.3333 | I16: =G16+H16 -> 12330.333 | J16: =J15+I16 -> 83303.333 | K16: =I16*12 -> 147964 | L16: =C16*Inputs!$E$6+D16*Inputs!$E$7+E16*Inputs!$E$8+F16*Inputs!$E$9 -> 34.8 | M16: =L16/Capacity!$B$15 -> 0.375
A17: 13 | B17: May 2027 | C17: 0 | D17: 1 | E17: 2 | F17: 0 | G17: =C17*Inputs!$B$6+D17*Inputs!$B$7+E17*Inputs!$B$8+F17*Inputs!$B$9 -> 10500 | H17: =IF(A17>=Inputs!$B$37,Inputs!$B$33*Inputs!$B$34+Inputs!$B$35/3*Inputs!$B$36,0) -> 1830.3333 | I17: =G17+H17 -> 12330.333 | J17: =J16+I17 -> 95633.667 | K17: =I17*12 -> 147964 | L17: =C17*Inputs!$E$6+D17*Inputs!$E$7+E17*Inputs!$E$8+F17*Inputs!$E$9 -> 34.8 | M17: =L17/Capacity!$B$15 -> 0.375
... A24: 20 | B24: Dec 2027 | C24: 0 | D24: 1 | E24: 1 | F24: 1 | G24: =C24*Inputs!$B$6+D24*Inputs!$B$7+E24*Inputs!$B$8+F24*Inputs!$B$9 -> 12500 | H24: =IF(A24>=Inputs!$B$37,Inputs!$B$33*Inputs!$B$34+Inputs!$B$35/3*Inputs!$B$36,0) -> 1830.3333 | I24: =G24+H24 -> 14330.333 | J24: =J23+I24 -> 191946 | K24: =I24*12 -> 171964 | L24: =C24*Inputs!$E$6+D24*Inputs!$E$7+E24*Inputs!$E$8+F24*Inputs!$E$9 -> 47.55 | M24: =L24/Capacity!$B$15 -> 0.51239224
B25: TOTAL / DEC 2027 | G25: =G24 -> 12500 | H25: =SUM(H5:H24) -> 32946 | I25: =SUM(I5:I24) -> 191946 | J25: =J24 -> 191946 | K25: =K24 -> 171964
B27: Target run-rate (annual) | C27: 150000
B28: Dec 2027 run-rate | C28: =K24 -> 171964
B29: Gap to target | C29: =C28-C27 -> 21964
B30: % of target | C30: =C28/C27 -> 1.1464267

Sheet Cash Flow
A1: Personal & Business Cash Flow
A2: W-2 income drops at the W-2 exit month from Inputs. Healthcare cost activates the month after.
A4: # | B4: Month | C4: Framework gross | D4: Less: Opex | E4: Less: SE tax reserve | F4: Net Framework cash | G4: W-2 gross | H4: W-2 net (post-tax) | I4: Healthcare | J4: Personal expenses | K4: Monthly cash delta | L4: Cash balance | M4: POC: MRR met? | N4: POC: Cash met?
A5: 1 | B5: May 2026 | C5: ='MRR Ramp'!I5 -> 0 | D5: =-Inputs!$B$27 -> -600 | E5: =-MAX(0,(C5+D5))*Inputs!$B$28 -> 0 | F5: =C5+D5+E5 -> -600 | G5: =IF(A5<Inputs!$B$24,Inputs!$B$23,0) -> 8000 | H5: =G5*(1-Inputs!$B$29) -> 6240 | I5: =IF(A5>=Inputs!$B$24,-Inputs!$B$26,0) -> 0 | J5: =-Inputs!$B$25 -> -6000 | K5: =F5+H5+I5+J5 -> -360 | L5: =Inputs!$B$30+K5 -> 19640 | M5: =IF(A5=Inputs!$B$24,IF('MRR Ramp'!G5>=Inputs!$B$40,"YES","NO"),"") | N5: =IF(A5=Inputs!$B$24,IF(L5>=Inputs!$B$25*Inputs!$B$41,"YES","NO"),"")
A6: 2 | B6: Jun 2026 | C6: ='MRR Ramp'!I6 -> 0 | D6: =-Inputs!$B$27 -> -600 | E6: =-MAX(0,(C6+D6))*Inputs!$B$28 -> 0 | F6: =C6+D6+E6 -> -600 | G6: =IF(A6<Inputs!$B$24,Inputs!$B$23,0) -> 8000 | H6: =G6*(1-Inputs!$B$29) -> 6240 | I6: =IF(A6>=Inputs!$B$24,-Inputs!$B$26,0) -> 0 | J6: =-Inputs!$B$25 -> -6000 | K6: =F6+H6+I6+J6 -> -360 | L6: =L5+K6 -> 19280 | M6: =IF(A6=Inputs!$B$24,IF('MRR Ramp'!G6>=Inputs!$B$40,"YES","NO"),"") | N6: =IF(A6=Inputs!$B$24,IF(L6>=Inputs!$B$25*Inputs!$B$41,"YES","NO"),"")
A7: 3 | B7: Jul 2026 | C7: ='MRR Ramp'!I7 -> 4330.3333 | D7: =-Inputs!$B$27 -> -600 | E7: =-MAX(0,(C7+D7))*Inputs!$B$28 -> -1044.4933 | F7: =C7+D7+E7 -> 2685.84 | G7: =IF(A7<Inputs!$B$24,Inputs!$B$23,0) -> 8000 | H7: =G7*(1-Inputs!$B$29) -> 6240 | I7: =IF(A7>=Inputs!$B$24,-Inputs!$B$26,0) -> 0 | J7: =-Inputs!$B$25 -> -6000 | K7: =F7+H7+I7+J7 -> 2925.84 | L7: =L6+K7 -> 22205.84 | M7: =IF(A7=Inputs!$B$24,IF('MRR Ramp'!G7>=Inputs!$B$40,"YES","NO"),"") | N7: =IF(A7=Inputs!$B$24,IF(L7>=Inputs!$B$25*Inputs!$B$41,"YES","NO"),"")
A8: 4 | B8: Aug 2026 | C8: ='MRR Ramp'!I8 -> 4330.3333 | D8: =-Inputs!$B$27 -> -600 | E8: =-MAX(0,(C8+D8))*Inputs!$B$28 -> -1044.4933 | F8: =C8+D8+E8 -> 2685.84 | G8: =IF(A8<Inputs!$B$24,Inputs!$B$23,0) -> 0 | H8: =G8*(1-Inputs!$B$29) -> 0 | I8: =IF(A8>=Inputs!$B$24,-Inputs!$B$26,0) -> -800 | J8: =-Inputs!$B$25 -> -6000 | K8: =F8+H8+I8+J8 -> -4114.16 | L8: =L7+K8 -> 18091.68 | M8: =IF(A8=Inputs!$B$24,IF('MRR Ramp'!G8>=Inputs!$B$40,"YES","NO"),"") -> NO | N8: =IF(A8=Inputs!$B$24,IF(L8>=Inputs!$B$25*Inputs!$B$41,"YES","NO"),"") -> NO
A9: 5 | B9: Sep 2026 | C9: ='MRR Ramp'!I9 -> 4330.3333 | D9: =-Inputs!$B$27 -> -600 | E9: =-MAX(0,(C9+D9))*Inputs!$B$28 -> -1044.4933 | F9: =C9+D9+E9 -> 2685.84 | G9: =IF(A9<Inputs!$B$24,Inputs!$B$23,0) -> 0 | H9: =G9*(1-Inputs!$B$29) -> 0 | I9: =IF(A9>=Inputs!$B$24,-Inputs!$B$26,0) -> -800 | J9: =-Inputs!$B$25 -> -6000 | K9: =F9+H9+I9+J9 -> -4114.16 | L9: =L8+K9 -> 13977.52 | M9: =IF(A9=Inputs!$B$24,IF('MRR Ramp'!G9>=Inputs!$B$40,"YES","NO"),"") | N9: =IF(A9=Inputs!$B$24,IF(L9>=Inputs!$B$25*Inputs!$B$41,"YES","NO"),"")
A10: 6 | B10: Oct 2026 | C10: ='MRR Ramp'!I10 -> 8330.3333 | D10: =-Inputs!$B$27 -> -600 | E10: =-MAX(0,(C10+D10))*Inputs!$B$28 -> -2164.4933 | F10: =C10+D10+E10 -> 5565.84 | G10: =IF(A10<Inputs!$B$24,Inputs!$B$23,0) -> 0 | H10: =G10*(1-Inputs!$B$29) -> 0 | I10: =IF(A10>=Inputs!$B$24,-Inputs!$B$26,0) -> -800 | J10: =-Inputs!$B$25 -> -6000 | K10: =F10+H10+I10+J10 -> -1234.16 | L10: =L9+K10 -> 12743.36 | M10: =IF(A10=Inputs!$B$24,IF('MRR Ramp'!G10>=Inputs!$B$40,"YES","NO"),"") | N10: =IF(A10=Inputs!$B$24,IF(L10>=Inputs!$B$25*Inputs!$B$41,"YES","NO"),"")
A11: 7 | B11: Nov 2026 | C11: ='MRR Ramp'!I11 -> 8330.3333 | D11: =-Inputs!$B$27 -> -600 | E11: =-MAX(0,(C11+D11))*Inputs!$B$28 -> -2164.4933 | F11: =C11+D11+E11 -> 5565.84 | G11: =IF(A11<Inputs!$B$24,Inputs!$B$23,0) -> 0 | H11: =G11*(1-Inputs!$B$29) -> 0 | I11: =IF(A11>=Inputs!$B$24,-Inputs!$B$26,0) -> -800 | J11: =-Inputs!$B$25 -> -6000 | K11: =F11+H11+I11+J11 -> -1234.16 | L11: =L10+K11 -> 11509.2 | M11: =IF(A11=Inputs!$B$24,IF('MRR Ramp'!G11>=Inputs!$B$40,"YES","NO"),"") | N11: =IF(A11=Inputs!$B$24,IF(L11>=Inputs!$B$25*Inputs!$B$41,"YES","NO"),"")
A12: 8 | B12: Dec 2026 | C12: ='MRR Ramp'!I12 -> 8330.3333 | D12: =-Inputs!$B$27 -> -600 | E12: =-MAX(0,(C12+D12))*Inputs!$B$28 -> -2164.4933 | F12: =C12+D12+E12 -> 5565.84 | G12: =IF(A12<Inputs!$B$24,Inputs!$B$23,0) -> 0 | H12: =G12*(1-Inputs!$B$29) -> 0 | I12: =IF(A12>=Inputs!$B$24,-Inputs!$B$26,0) -> -800 | J12: =-Inputs!$B$25 -> -6000 | K12: =F12+H12+I12+J12 -> -1234.16 | L12: =L11+K12 -> 10275.04 | M12: =IF(A12=Inputs!$B$24,IF('MRR Ramp'!G12>=Inputs!$B$40,"YES","NO"),"") | N12: =IF(A12=Inputs!$B$24,IF(L12>=Inputs!$B$25*Inputs!$B$41,"YES","NO"),"")
A13: 9 | B13: Jan 2027 | C13: ='MRR Ramp'!I13 -> 8330.3333 | D13: =-Inputs!$B$27 -> -600 | E13: =-MAX(0,(C13+D13))*Inputs!$B$28 -> -2164.4933 | F13: =C13+D13+E13 -> 5565.84 | G13: =IF(A13<Inputs!$B$24,Inputs!$B$23,0) -> 0 | H13: =G13*(1-Inputs!$B$29) -> 0 | I13: =IF(A13>=Inputs!$B$24,-Inputs!$B$26,0) -> -800 | J13: =-Inputs!$B$25 -> -6000 | K13: =F13+H13+I13+J13 -> -1234.16 | L13: =L12+K13 -> 9040.88 | M13: =IF(A13=Inputs!$B$24,IF('MRR Ramp'!G13>=Inputs!$B$40,"YES","NO"),"") | N13: =IF(A13=Inputs!$B$24,IF(L13>=Inputs!$B$25*Inputs!$B$41,"YES","NO"),"")
A14: 10 | B14: Feb 2027 | C14: ='MRR Ramp'!I14 -> 12330.333 | D14: =-Inputs!$B$27 -> -600 | E14: =-MAX(0,(C14+D14))*Inputs!$B$28 -> -3284.4933 | F14: =C14+D14+E14 -> 8445.84 | G14: =IF(A14<Inputs!$B$24,Inputs!$B$23,0) -> 0 | H14: =G14*(1-Inputs!$B$29) -> 0 | I14: =IF(A14>=Inputs!$B$24,-Inputs!$B$26,0) -> -800 | J14: =-Inputs!$B$25 -> -6000 | K14: =F14+H14+I14+J14 -> 1645.84 | L14: =L13+K14 -> 10686.72 | M14: =IF(A14=Inputs!$B$24,IF('MRR Ramp'!G14>=Inputs!$B$40,"YES","NO"),"") | N14: =IF(A14=Inputs!$B$24,IF(L14>=Inputs!$B$25*Inputs!$B$41,"YES","NO"),"")
A15: 11 | B15: Mar 2027 | C15: ='MRR Ramp'!I15 -> 12330.333 | D15: =-Inputs!$B$27 -> -600 | E15: =-MAX(0,(C15+D15))*Inputs!$B$28 -> -3284.4933 | F15: =C15+D15+E15 -> 8445.84 | G15: =IF(A15<Inputs!$B$24,Inputs!$B$23,0) -> 0 | H15: =G15*(1-Inputs!$B$29) -> 0 | I15: =IF(A15>=Inputs!$B$24,-Inputs!$B$26,0) -> -800 | J15: =-Inputs!$B$25 -> -6000 | K15: =F15+H15+I15+J15 -> 1645.84 | L15: =L14+K15 -> 12332.56 | M15: =IF(A15=Inputs!$B$24,IF('MRR Ramp'!G15>=Inputs!$B$40,"YES","NO"),"") | N15: =IF(A15=Inputs!$B$24,IF(L15>=Inputs!$B$25*Inputs!$B$41,"YES","NO"),"")
A16: 12 | B16: Apr 2027 | C16: ='MRR Ramp'!I16 -> 12330.333 | D16: =-Inputs!$B$27 -> -600 | E16: =-MAX(0,(C16+D16))*Inputs!$B$28 -> -3284.4933 | F16: =C16+D16+E16 -> 8445.84 | G16: =IF(A16<Inputs!$B$24,Inputs!$B$23,0) -> 0 | H16: =G16*(1-Inputs!$B$29) -> 0 | I16: =IF(A16>=Inputs!$B$24,-Inputs!$B$26,0) -> -800 | J16: =-Inputs!$B$25 -> -6000 | K16: =F16+H16+I16+J16 -> 1645.84 | L16: =L15+K16 -> 13978.4 | M16: =IF(A16=Inputs!$B$24,IF('MRR Ramp'!G16>=Inputs!$B$40,"YES","NO"),"") | N16: =IF(A16=Inputs!$B$24,IF(L16>=Inputs!$B$25*Inputs!$B$41,"YES","NO"),"")
A17: 13 | B17: May 2027 | C17: ='MRR Ramp'!I17 -> 12330.333 | D17: =-Inputs!$B$27 -> -600 | E17: =-MAX(0,(C17+D17))*Inputs!$B$28 -> -3284.4933 | F17: =C17+D17+E17 -> 8445.84 | G17: =IF(A17<Inputs!$B$24,Inputs!$B$23,0) -> 0 | H17: =G17*(1-Inputs!$B$29) -> 0 | I17: =IF(A17>=Inputs!$B$24,-Inputs!$B$26,0) -> -800 | J17: =-Inputs!$B$25 -> -6000 | K17: =F17+H17+I17+J17 -> 1645.84 | L17: =L16+K17 -> 15624.24 | M17: =IF(A17=Inputs!$B$24,IF('MRR Ramp'!G17>=Inputs!$B$40,"YES","NO"),"") | N17: =IF(A17=Inputs!$B$24,IF(L17>=Inputs!$B$25*Inputs!$B$41,"YES","NO"),"")
... A24: 20 | B24: Dec 2027 | C24: ='MRR Ramp'!I24 -> 14330.333 | D24: =-Inputs!$B$27 -> -600 | E24: =-MAX(0,(C24+D24))*Inputs!$B$28 -> -3844.4933 | F24: =C24+D24+E24 -> 9885.84 | G24: =IF(A24<Inputs!$B$24,Inputs!$B$23,0) -> 0 | H24: =G24*(1-Inputs!$B$29) -> 0 | I24: =IF(A24>=Inputs!$B$24,-Inputs!$B$26,0) -> -800 | J24: =-Inputs!$B$25 -> -6000 | K24: =F24+H24+I24+J24 -> 3085.84 | L24: =L23+K24 -> 34345.12 | M24: =IF(A24=Inputs!$B$24,IF('MRR Ramp'!G24>=Inputs!$B$40,"YES","NO"),"") | N24: =IF(A24=Inputs!$B$24,IF(L24>=Inputs!$B$25*Inputs!$B$41,"YES","NO"),"")
